{
    "driverList": {
        "data": {
            "count": 1633,
            "rows": [
                {
                    "driver_name": "1141"
                },
                {
                    "driver_name": "2"
                },
                {
                    "driver_name": "3"
                }
            ]
        }
    },
    "r99TransectionData" : {
        "data" : {
            "count": 1633,
            "rows": [
                {
                    "driver_name": "G",
                    "vehicle_id": "23421",
                    "department": 34992,
                    "transaction_date": "2024-11-30",
                    "location_id": 18,
                    "fuel_consumption": 0,
                    "fuelLocationName": "Kern, CA",
                    "fuelConstantName": "rDiesel"
                },
                {
                    "driver_name": "NA",
                    "vehicle_id": "NA",
                    "department": 34992,
                    "transaction_date": "2024-11-30",
                    "location_id": 18,
                    "fuel_consumption": 0,
                    "fuelLocationName": "Kern, CA",
                    "fuelConstantName": "rDiesel"
                },
                {
                    "driver_name": "G",
                    "vehicle_id": "23421",
                    "department": 34992,
                    "transaction_date": "2024-11-30",
                    "location_id": 18,
                    "fuel_consumption": 0,
                    "fuelLocationName": "Kern, CA",
                    "fuelConstantName": "rDiesel"
                }
            ]
        }
    }
}